synutility/__init__.py
synutility/misc.py
synutility/SynAAM/__init__.py
synutility/SynAAM/aam_validator.py
synutility/SynAAM/inference.py
synutility/SynAAM/its_builder.py
synutility/SynAAM/its_construction.py
synutility/SynAAM/misc.py
synutility/SynAAM/normalize_aam.py
synutility/SynAAM/partial_expand.py
synutility/SynChem/__init__.py
synutility/SynChem/Fingerprint/__init__.py
synutility/SynChem/Fingerprint/fp_calculator.py
synutility/SynChem/Fingerprint/smiles_featurizer.py
synutility/SynChem/Fingerprint/transformation_fp.py
synutility/SynChem/Molecule/__init__.py
synutility/SynChem/Molecule/standardize.py
synutility/SynChem/Reaction/__init__.py
synutility/SynChem/Reaction/balance_check.py
synutility/SynChem/Reaction/cleanning.py
synutility/SynChem/Reaction/deionize.py
synutility/SynChem/Reaction/neutralize.py
synutility/SynChem/Reaction/reagent.py
synutility/SynChem/Reaction/resolve_issue.py
synutility/SynChem/Reaction/standardize.py
synutility/SynChem/Reaction/tautomerize.py
synutility/SynGraph/__init__.py
synutility/SynGraph/Cluster/__init__.py
synutility/SynGraph/Cluster/batch_cluster.py
synutility/SynGraph/Cluster/graph_cluster.py
synutility/SynGraph/Descriptor/__init__.py
synutility/SynGraph/Descriptor/graph_descriptors.py
synutility/SynGraph/Descriptor/graph_signature.py
synutility/SynGraph/Fingerprint/__init__.py
synutility/SynGraph/Fingerprint/graph_fps.py
synutility/SynGraph/Fingerprint/hash_fps.py
synutility/SynGraph/Fingerprint/morgan_fps.py
synutility/SynGraph/Fingerprint/path_fps.py
synutility/SynGraph/GML/__init__.py
synutility/SynGraph/GML/morphism.py
synutility/SynGraph/GML/parse_rule.py
synutility/SynGraph/Transform/__init__.py
synutility/SynGraph/Transform/core_engine.py
synutility/SynGraph/Transform/multi_step.py
synutility/SynGraph/Transform/multi_step_aam.py
synutility/SynGraph/Transform/reagent.py
synutility/SynGraph/Transform/rule_apply.py
synutility/SynIO/__init__.py
synutility/SynIO/data_type.py
synutility/SynIO/debug.py
synutility-0.0.14.dist-info/METADATA
synutility-0.0.14.dist-info/WHEEL
synutility-0.0.14.dist-info/licenses/LICENSE
synutility-0.0.14.dist-info/RECORD
