Metadata-Version: 2.4
Name: synutility
Version: 0.0.14
Summary: Utility for reaction modeling using graph grammar
Project-URL: homepage, https://github.com/TieuLongPhan/SynUtils
Project-URL: source, https://github.com/TieuLongPhan/SynUtils
Project-URL: issues, https://github.com/TieuLongPhan/SynUtils/issues
Project-URL: documentation, https://tieulongphan.github.io/SynUtils/
Author-email: Tieu Long Phan <tieu@bioinf.uni-leipzig.de>
License-File: LICENSE
Classifier: License :: OSI Approved :: MIT License
Classifier: Operating System :: OS Independent
Classifier: Programming Language :: Python :: 3
Requires-Python: >=3.11
Requires-Dist: networkx>=3.3
Requires-Dist: pandas>=1.5.3
Requires-Dist: rdkit>=2024.3.3
Requires-Dist: requests>=2.32.3
Requires-Dist: scikit-learn>=1.4.0
Requires-Dist: seaborn>=0.13.2
Provides-Extra: all
Requires-Dist: drfp==0.3.6; extra == 'all'
Requires-Dist: fgutils>=0.1.3; extra == 'all'
Requires-Dist: rxn-chem-utils==1.5.0; extra == 'all'
Requires-Dist: rxn-utils==2.0.0; extra == 'all'
Requires-Dist: rxnmapper==0.3.0; extra == 'all'
Requires-Dist: xgboost>=2.1.1; extra == 'all'
